opus/__init__.py
opus/api.py
opus/categories.py
opus/data.py
opus/fields.py
opus/files.py
opus/images.py
opus/metadata.py
opus/mults.py
opus/range.py
opus/url.py
opus/wget.py
opus/cli/__init__.py
opus/cli/cassini.py
opus/cli/cli.py
opus_seti-0.4.2.dist-info/AUTHORS
opus_seti-0.4.2.dist-info/LICENSE.md
opus_seti-0.4.2.dist-info/METADATA
opus_seti-0.4.2.dist-info/WHEEL
opus_seti-0.4.2.dist-info/entry_points.txt
opus_seti-0.4.2.dist-info/pbr.json
opus_seti-0.4.2.dist-info/top_level.txt
opus_seti-0.4.2.dist-info/RECORD
