Metadata-Version: 2.1
Name: opus-seti
Version: 0.4.2
Summary: Python package for OPUS (NASA-PDS/Seti) search tool API
Home-page: http://github.com/seignovert/python-opus-seti
Author: Benoit Seignovert
Author-email: python@seignovert.fr
License: MIT
Keywords: NASA,Seti,Ring-node,API
Platform: UNKNOWN
Classifier: Development Status :: 4 - Beta
Classifier: Natural Language :: English
Classifier: License :: OSI Approved :: MIT License
Classifier: Programming Language :: Python
Classifier: Programming Language :: Python :: 2.7
Classifier: Programming Language :: Python :: 3.6
Classifier: Topic :: Scientific/Engineering
Classifier: Topic :: Scientific/Engineering :: Astronomy
Classifier: Topic :: Scientific/Engineering :: Atmospheric Science
Classifier: Topic :: Scientific/Engineering :: Physics
Classifier: Topic :: Scientific/Engineering :: Visualization
Requires-Dist: requests
Requires-Dist: six
Requires-Dist: argparse
